manumaqueda_distributions/Binomialdistribution.py
manumaqueda_distributions/Gaussiandistribution.py
manumaqueda_distributions/Generaldistribution.py
manumaqueda_distributions/__init__.py
manumaqueda_distributions-0.1.dist-info/DESCRIPTION.rst
manumaqueda_distributions-0.1.dist-info/METADATA
manumaqueda_distributions-0.1.dist-info/RECORD
manumaqueda_distributions-0.1.dist-info/WHEEL
manumaqueda_distributions-0.1.dist-info/metadata.json
manumaqueda_distributions-0.1.dist-info/top_level.txt
